transactional_mail/__init__.py
transactional_mail/admin.py
transactional_mail/apps.py
transactional_mail/emails.py
transactional_mail/models.py
transactional_mail/registry.py
transactional_mail/tests.py
django_transactional_mail-0.2.2.dist-info/LICENSE
django_transactional_mail-0.2.2.dist-info/METADATA
django_transactional_mail-0.2.2.dist-info/WHEEL
django_transactional_mail-0.2.2.dist-info/top_level.txt
django_transactional_mail-0.2.2.dist-info/RECORD
