Metadata-Version: 2.1
Name: django-transactional-mail
Version: 0.2.2
Summary: Transactional emails in Django projects made easy
Home-page: https://github.com/vinaypai/django-transactional-mail/
Author: Vinay Pai
Author-email: vinay@vinaypai.com
License: UNKNOWN
Platform: UNKNOWN
Classifier: Development Status :: 3 - Alpha
Classifier: Environment :: Web Environment
Classifier: Framework :: Django
Classifier: Intended Audience :: Developers
Classifier: License :: OSI Approved :: MIT License
Classifier: Operating System :: OS Independent
Classifier: Programming Language :: Python :: 3
Classifier: Topic :: Communications :: Email
Requires-Dist: django (>=2.2)
Requires-Dist: django-render-block (>=0.5)
Requires-Dist: html2text (>=2017)
Requires-Dist: cssutils (>=1.0.2)
